Minerals.py
Minerals-0.0.2.dist-info/LICENSE.txt
Minerals-0.0.2.dist-info/METADATA
Minerals-0.0.2.dist-info/WHEEL
Minerals-0.0.2.dist-info/top_level.txt
Minerals-0.0.2.dist-info/RECORD
