Metadata-Version: 2.1
Name: Minerals
Version: 0.0.2
Summary: Clay
Home-page: https://github.com/farooqad0/ClayMineralsIdentify
Author: Farooq Arshad
Author-email: farooqad0@gmail.com
License: UNKNOWN
Platform: UNKNOWN
Classifier: Intended Audience :: Education
Classifier: Operating System :: Microsoft :: Windows :: Windows 10
Classifier: License :: OSI Approved :: GNU Affero General Public License v3 or later (AGPLv3+)
Classifier: Programming Language :: Python :: 3
